py3link/__init__.py
py3link/cli.py
py3link/downloader.py
py3link-0.1.6.dist-info/licenses/LICENSE
py3link-0.1.6.dist-info/METADATA
py3link-0.1.6.dist-info/WHEEL
py3link-0.1.6.dist-info/entry_points.txt
py3link-0.1.6.dist-info/top_level.txt
py3link-0.1.6.dist-info/RECORD
