Metadata-Version: 2.4
Name: Py3link
Version: 0.1.6
Summary: A powerful and beautiful Python library for downloading files and videos from various sources.
Home-page: https://github.com/KinderModddins/py3link
Author: MAKCNMOB
Author-email: mail@example.com
License: MIT
Classifier: Programming Language :: Python :: 3
Classifier: License :: OSI Approved :: MIT License
Classifier: Operating System :: OS Independent
License-File: LICENSE
Requires-Dist: requests
Requires-Dist: yt-dlp
Requires-Dist: tqdm
Dynamic: author
Dynamic: author-email
Dynamic: classifier
Dynamic: description
Dynamic: description-content-type
Dynamic: home-page
Dynamic: license
Dynamic: license-file
Dynamic: requires-dist
Dynamic: summary
